hub_v1/__init__.py
hub_v1/__main__.py
hub_v1/config.py
hub_v1/defaults.py
hub_v1/exceptions.py
hub_v1/log.py
hub_v1/png_numcodec.py
hub_v1/report.py
hub_v1/test_numcodecs.py
hub_v1/url.py
hub_v1/utils.py
hub_v1/version.py
hub_v1/api/__init__.py
hub_v1/api/compute_list.py
hub_v1/api/dataset.py
hub_v1/api/dataset_utils.py
hub_v1/api/datasetview.py
hub_v1/api/integrations.py
hub_v1/api/objectview.py
hub_v1/api/sharded_datasetview.py
hub_v1/api/tensorview.py
hub_v1/api/versioning.py
hub_v1/auto/__init__.py
hub_v1/auto/infer.py
hub_v1/auto/util.py
hub_v1/auto/computer_vision/__init__.py
hub_v1/auto/computer_vision/classification.py
hub_v1/auto/tabular/__init__.py
hub_v1/auto/tabular/csv.py
hub_v1/cli/__init__.py
hub_v1/cli/auth.py
hub_v1/cli/command.py
hub_v1/cli/dev.py
hub_v1/cli/local.py
hub_v1/client/__init__.py
hub_v1/client/auth.py
hub_v1/client/base.py
hub_v1/client/hub_control.py
hub_v1/client/token_manager.py
hub_v1/codec/__init__.py
hub_v1/codec/base.py
hub_v1/codec/default.py
hub_v1/codec/gzip.py
hub_v1/codec/image.py
hub_v1/codec/jpeg.py
hub_v1/codec/lz4.py
hub_v1/codec/png.py
hub_v1/codec/zip.py
hub_v1/codec/zlib.py
hub_v1/collections/__init__.py
hub_v1/collections/_chunk_utils.py
hub_v1/collections/_store_version.py
hub_v1/collections/client_manager.py
hub_v1/collections/dataset/__init__.py
hub_v1/collections/dataset/core.py
hub_v1/collections/tensor/__init__.py
hub_v1/collections/tensor/core.py
hub_v1/compute/__init__.py
hub_v1/compute/ray.py
hub_v1/compute/transform.py
hub_v1/schema/__init__.py
hub_v1/schema/audio.py
hub_v1/schema/bbox.py
hub_v1/schema/class_label.py
hub_v1/schema/deserialize.py
hub_v1/schema/features.py
hub_v1/schema/image.py
hub_v1/schema/mask.py
hub_v1/schema/polygon.py
hub_v1/schema/segmentation.py
hub_v1/schema/sequence.py
hub_v1/schema/serialize.py
hub_v1/schema/text.py
hub_v1/schema/video.py
hub_v1/store/__init__.py
hub_v1/store/azure_fs.py
hub_v1-1.3.9.dist-info/DESCRIPTION.rst
hub_v1-1.3.9.dist-info/METADATA
hub_v1-1.3.9.dist-info/RECORD
hub_v1-1.3.9.dist-info/WHEEL
hub_v1-1.3.9.dist-info/entry_points.txt
hub_v1-1.3.9.dist-info/metadata.json
hub_v1-1.3.9.dist-info/top_level.txt
hub_v1-1.3.9.dist-info/zip-safe
