Metadata-Version: 2.0
Name: hub-v1
Version: 1.3.9
Summary: Activeloop Hub
Home-page: https://github.com/activeloopai/Hub
Author: Snark AI Inc.
Author-email: support@activeloop.ai
License: MPL 2.0
Project-URL: Documentation, https://docs.activeloop.ai/
Project-URL: Source, https://github.com/activeloopai/Hub
Keywords: snark-hub
Platform: UNKNOWN
Classifier: License :: OSI Approved :: Mozilla Public License 2.0 (MPL 2.0)
Classifier: Programming Language :: Python :: 3
Classifier: Programming Language :: Python :: 3.6
Classifier: Programming Language :: Python :: 3.7
Classifier: Programming Language :: Python :: 3.8
Classifier: Programming Language :: Python :: 3.9
Classifier: Programming Language :: Python :: 3 :: Only
Requires-Python: >=3.6
License-File: LICENSE
Requires-Dist: click (<8,>=6.7)
Requires-Dist: numpy (<2,>=1.17)
Requires-Dist: requests (<3,>=2)
Requires-Dist: fsspec (<2022,>=0.8)
Requires-Dist: gcsfs (<0.7,>=0.6.2)
Requires-Dist: s3fs (<0.5.2,==0.4.2)
Requires-Dist: boto3 (==1.17.59)
Requires-Dist: lz4 (<4,>=3)
Requires-Dist: zarr (<2.8,>=2.4)
Requires-Dist: tqdm (<5,>=4.1)
Requires-Dist: azure-storage-blob (<13,>=12)
Requires-Dist: pathos (<0.3,>=0.2)
Requires-Dist: humbug (<0.3,>=0.1.14)
Requires-Dist: Pillow (>=6)
Requires-Dist: msgpack (>=0.6)
Requires-Dist: psutil (>=5.8)
Requires-Dist: cachey (>=0.2.1)
